scloud_api/__init__.py
scloud_api/api/__init__.py
scloud_api/api/catalog/__init__.py
scloud_api/api/catalog/catalog.py
scloud_api/api/companies/__init__.py
scloud_api/api/companies/companies.py
scloud_api/api/exports/__init__.py
scloud_api/api/exports/exports.py
scloud_api/api/orders/__init__.py
scloud_api/api/orders/orders.py
scloud_api/api/queued_jobs/__init__.py
scloud_api/api/queued_jobs/queued_jobs.py
scloud_api/api/settings/__init__.py
scloud_api/api/settings/settings.py
scloud_api/api/warehouses/__init__.py
scloud_api/api/warehouses/warehouses.py
scloud_api/auth/__init__.py
scloud_api/auth/auth_token_client.py
scloud_api/auth/auth_token_response.py
scloud_api/auth/credentials.py
scloud_api/auth/exceptions.py
scloud_api/base/ApiResponse.py
scloud_api/base/__init__.py
scloud_api/base/client.py
scloud_api-0.8.11.dist-info/licenses/LICENSE
tests/__init__.py
tests/client/__init__.py
tests/client/test_auth.py
scloud_api-0.8.11.dist-info/METADATA
scloud_api-0.8.11.dist-info/WHEEL
scloud_api-0.8.11.dist-info/top_level.txt
scloud_api-0.8.11.dist-info/RECORD
